pioreactor_basic_auth_for_ui/LEADER_ONLY
pioreactor_basic_auth_for_ui/__init__.py
pioreactor_basic_auth_for_ui/post_install.sh
pioreactor_basic_auth_for_ui/pre_uninstall.sh
pioreactor_basic_auth_for_ui-0.0.3.dist-info/LICENSE.txt
pioreactor_basic_auth_for_ui-0.0.3.dist-info/METADATA
pioreactor_basic_auth_for_ui-0.0.3.dist-info/WHEEL
pioreactor_basic_auth_for_ui-0.0.3.dist-info/entry_points.txt
pioreactor_basic_auth_for_ui-0.0.3.dist-info/top_level.txt
pioreactor_basic_auth_for_ui-0.0.3.dist-info/RECORD
