Metadata-Version: 2.1
Name: pioreactor-basic-auth-for-ui
Version: 0.0.3
Summary: Adding basic auth to the Pioreactor UI
Home-page: 
Author: Cameron Davidson-Pilon
Author-email: hello@pioreactor.com
License-File: LICENSE.txt
